happy_valentines/__init__.py
happy_valentines/main.py
happy_valentines-0.1.0.dist-info/METADATA
happy_valentines-0.1.0.dist-info/WHEEL
happy_valentines-0.1.0.dist-info/entry_points.txt
happy_valentines-0.1.0.dist-info/top_level.txt
happy_valentines-0.1.0.dist-info/RECORD
