Metadata-Version: 2.2
Name: happy_valentines
Version: 0.1.0
Summary: A package that generates daily love poems using gpt-4o.
Author: Liz Tan
Author-email: elizabethsztan@gmail.com
Classifier: Programming Language :: Python :: 3
Classifier: License :: OSI Approved :: MIT License
Classifier: Operating System :: OS Independent
Requires-Python: >=3.7
Requires-Dist: openai>1.0.0
Requires-Dist: rich
Dynamic: author
Dynamic: author-email
Dynamic: classifier
Dynamic: requires-dist
Dynamic: requires-python
Dynamic: summary
